peripy/__init__.py
peripy/cli.py
peripy/correction.c
peripy/correction.cp37-win_amd64.pyd
peripy/create_crack.c
peripy/create_crack.cp37-win_amd64.pyd
peripy/integrators.py
peripy/model.py
peripy/peridynamics.c
peripy/peridynamics.cp37-win_amd64.pyd
peripy/spatial.c
peripy/spatial.cp37-win_amd64.pyd
peripy/utilities.py
peripy/cl/__init__.py
peripy/cl/euler.cl
peripy/cl/euler_cromer.cl
peripy/cl/peridynamics.cl
peripy/cl/utilities.py
peripy/cl/velocity_verlet.cl
peripy/examples/__init__.py
peripy/examples/run.py
peripy/examples/example1/example.py
peripy/examples/example1/test.vtk
peripy/examples/example2/1650beam13539.msh
peripy/examples/example2/example.py
peripy/test/__init__.py
peripy/test/conftest.py
peripy/test/test_cl_euler.py
peripy/test/test_cl_euler_cromer.py
peripy/test/test_cl_peridynamics.py
peripy/test/test_cl_utilities.py
peripy/test/test_cl_velocity_verlet.py
peripy/test/test_correction.py
peripy/test/test_integrators.py
peripy/test/test_model.py
peripy/test/test_neighbour_list.py
peripy/test/test_peridynamics.py
peripy/test/test_regression.py
peripy/test/test_spatial.py
peripy/test/test_utilities.py
peripy/test/data/example_mesh.vtk
peripy/test/data/example_mesh_3d.vtk
peripy/test/data/example_mesh_large.msh
peripy/test/data/example_mesh_transfinite.msh
peripy/test/data/expected_accelerations_velocity_verlet.npy
peripy/test/data/expected_bc_types.npy
peripy/test/data/expected_bc_values.npy
peripy/test/data/expected_bond_types.npy
peripy/test/data/expected_bond_types_cl.npy
peripy/test/data/expected_connectivity.npz
peripy/test/data/expected_connectivity_basic.npz
peripy/test/data/expected_connectivity_basic_cl.npz
peripy/test/data/expected_connectivity_cl.npz
peripy/test/data/expected_connectivity_crack.npz
peripy/test/data/expected_connectivity_crack_cl.npz
peripy/test/data/expected_connectivity_euler_cromer_cl.npz
peripy/test/data/expected_connectivity_velocity_verlet.npz
peripy/test/data/expected_connectivity_velocity_verlet_cl.npz
peripy-1.0.0.dist-info/LICENSE.rst
peripy-1.0.0.dist-info/METADATA
peripy-1.0.0.dist-info/WHEEL
peripy-1.0.0.dist-info/entry_points.txt
peripy-1.0.0.dist-info/top_level.txt
peripy-1.0.0.dist-info/RECORD
