Metadata-Version: 2.1
Name: peripy
Version: 1.0.0
Summary: A fast OpenCL Peridynamics package for python
Home-page: https://github.com/alan-turing-institute/Probabilistic-Peridynamics
Author: Jim Madge, Ben Boys, Tim Dodwell, Greg Mingas
License: MIT
Platform: UNKNOWN
Requires-Dist: meshio
Requires-Dist: numpy
Requires-Dist: pyopencl
Requires-Dist: scipy
Requires-Dist: tqdm
Requires-Dist: h5py
Requires-Dist: sklearn
Requires-Dist: sphinx-rtd-theme
